LICENCE
MANIFEST.in
Makefile
README.md
changelog.txt
logo.png
pyproject.toml
setup.py
/Users/giulianoiorio/Documents/sevn_public/SEVNpy/sevnpy/sevn/src/binarywrap.cpp
/Users/giulianoiorio/Documents/sevn_public/SEVNpy/sevnpy/sevn/src/iowrap.cpp
/Users/giulianoiorio/Documents/sevn_public/SEVNpy/sevnpy/sevn/src/sevnwrap.cpp
/Users/giulianoiorio/Documents/sevn_public/SEVNpy/sevnpy/sevn/src/starwrap.cpp
/Users/giulianoiorio/Documents/sevn_public/SEVNpy/sevnpy/sevn/src/wraputils.cpp
/Users/giulianoiorio/Documents/sevn_public/src/binstar/BinaryProperty.cpp
/Users/giulianoiorio/Documents/sevn_public/src/binstar/MTstability.cpp
/Users/giulianoiorio/Documents/sevn_public/src/binstar/Orbit.cpp
/Users/giulianoiorio/Documents/sevn_public/src/binstar/Processes.cpp
/Users/giulianoiorio/Documents/sevn_public/src/binstar/binstar.cpp
/Users/giulianoiorio/Documents/sevn_public/src/binstar/qcrit.cpp
/Users/giulianoiorio/Documents/sevn_public/src/binstar/procs/Circularisation.cpp
/Users/giulianoiorio/Documents/sevn_public/src/binstar/procs/Collision.cpp
/Users/giulianoiorio/Documents/sevn_public/src/binstar/procs/Hardening.cpp
/Users/giulianoiorio/Documents/sevn_public/src/general/IO.cpp
/Users/giulianoiorio/Documents/sevn_public/src/general/lookup_and_phases.cpp
/Users/giulianoiorio/Documents/sevn_public/src/general/params.cpp
/Users/giulianoiorio/Documents/sevn_public/src/general/starparameter.cpp
/Users/giulianoiorio/Documents/sevn_public/src/general/utils/evolve.cpp
/Users/giulianoiorio/Documents/sevn_public/src/general/utils/sevnlog.cpp
/Users/giulianoiorio/Documents/sevn_public/src/general/utils/utilities.cpp
/Users/giulianoiorio/Documents/sevn_public/src/star/globalproperties.cpp
/Users/giulianoiorio/Documents/sevn_public/src/star/property.cpp
/Users/giulianoiorio/Documents/sevn_public/src/star/remnant.cpp
/Users/giulianoiorio/Documents/sevn_public/src/star/star.cpp
/Users/giulianoiorio/Documents/sevn_public/src/star/lambdas/lambda_klencki21.cpp
SEVNpy.egg-info/PKG-INFO
SEVNpy.egg-info/SOURCES.txt
SEVNpy.egg-info/dependency_links.txt
SEVNpy.egg-info/top_level.txt
