Metadata-Version: 2.1
Name: SEVNpy
Version: 0.2.3
Summary: A Python companion module for SEVN
Author: Giuliano Iorio
Author-email: giuliano.iorio.astro@gmail.com
License: MIT
Requires-Python: >=3.7
License-File: LICENCE
